base58/__init__.py
base58/__main__.py
base58/py.typed
base58-2.0.1.dist-info/COPYING
base58-2.0.1.dist-info/METADATA
base58-2.0.1.dist-info/WHEEL
base58-2.0.1.dist-info/entry_points.txt
base58-2.0.1.dist-info/top_level.txt
base58-2.0.1.dist-info/RECORD
